pycarbon/__init__.py
pycarbon/reader.py
pycarbon/sdk/ArrowCarbonReader.py
pycarbon/sdk/CarbonReader.py
pycarbon/sdk/CarbonSchemaReader.py
pycarbon/sdk/CarbonWriter.py
pycarbon/sdk/Configuration.py
pycarbon/sdk/Constants.py
pycarbon/sdk/SDKUtil.py
pycarbon/sdk/__init__.py
pycarbon/tests/__init__.py
pycarbon/tests/test.py
pycarbon/tests/sdk/__init__.py
pycarbon/tests/sdk/test_read_write_carbon.py
pycarbon_sdk-0.1.0.dist-info/METADATA
pycarbon_sdk-0.1.0.dist-info/WHEEL
pycarbon_sdk-0.1.0.dist-info/top_level.txt
pycarbon_sdk-0.1.0.dist-info/RECORD
