Metadata-Version: 2.1
Name: pycarbon-sdk
Version: 0.1.0
Summary: Pycarbon is a library that optimizes data access for AI based on CarbonData files,  and it is based on Petastorm.
Home-page: https://github.com/apache/carbondata
Author: Apache CarbonData
License: Apache License, Version 2.0
Platform: UNKNOWN
Classifier: Environment :: Console
Classifier: Environment :: Web Environment
Classifier: Intended Audience :: Developers
Classifier: Intended Audience :: Science/Research
Classifier: License :: OSI Approved :: Apache Software License
Classifier: Programming Language :: Python :: 2.7
Classifier: Programming Language :: Python :: 3.4
Classifier: Programming Language :: Python :: 3.5
Classifier: Programming Language :: Python :: 3.6
Requires-Dist: jnius (>=1.1.0)
Requires-Dist: pyjnius (>=1.2.0)
Provides-Extra: docs
Requires-Dist: sphinx (==1.2.2) ; extra == 'docs'
Requires-Dist: alabaster (==0.7.11) ; extra == 'docs'
Provides-Extra: test
Requires-Dist: Pillow (>=3.0) ; extra == 'test'
Requires-Dist: codecov (>=2.0.15) ; extra == 'test'
Requires-Dist: mock (>=2.0.0) ; extra == 'test'
Requires-Dist: opencv-python (>=3.2.0.6) ; extra == 'test'
Requires-Dist: flake8 ; extra == 'test'
Requires-Dist: pylint (>=1.9) ; extra == 'test'
Requires-Dist: pytest (>=3.0.0) ; extra == 'test'
Requires-Dist: pytest-cov (>=2.5.1) ; extra == 'test'
Requires-Dist: pytest-forked (>=0.2) ; extra == 'test'
Requires-Dist: pytest-logger (>=0.4.0) ; extra == 'test'
Requires-Dist: pytest-timeout (>=1.3.3) ; extra == 'test'
Requires-Dist: pytest-xdist ; extra == 'test'
Requires-Dist: s3fs (>=0.0.1) ; extra == 'test'
Provides-Extra: torch
Requires-Dist: torchvision (>=0.2.1) ; extra == 'torch'
